src/sample_math/__init__.py
src/sample_math/arithmetic.py
openap_pypi_framework-0.1.1.dist-info/METADATA
openap_pypi_framework-0.1.1.dist-info/WHEEL
openap_pypi_framework-0.1.1.dist-info/RECORD
