Metadata-Version: 2.1
Name: openap-pypi-framework
Version: 0.1.1
Summary: 
Author: Savan Rupani
Author-email: savan.rupani@outlook.com
Requires-Python: >=3.11,<4.0
Classifier: Programming Language :: Python :: 3
Classifier: Programming Language :: Python :: 3.11
Classifier: Programming Language :: Python :: 3.12
